{
    "method": "random",
    "name": "Blank Name",
    "metric": {
      "goal": "maximize",
      "name": "best_val_bal_acc"
    },
    "parameters": {
      "batch_size": {
        "values": [16]
      },
      "epochs": {
        "values": [150]
      },
      "lr": {
        "values": [0.0010]
      },
      "weight_decay": {
        "values": [0.004178]
      },
      "hidden_channels": {
        "values": [64]
      },
      "dropout": {
        "values": [0.3]
      },
      "num_layers": {
        "values": [1]
      },
      "aggregation_mode": {
        "values": ["max_mean"]
      },
      "pre_layers": {
        "values": [2]
      },
      "post_layers": {
        "values": [1]
      },
      "final_layers": {
        "values": [4]
      },
      "batch_norm": {
        "values": [true]
      },
      "hetero_conns": {
        "values": [true]
      },
      "faz_conns": {
        "values": [true]
      },
      "conv_aggr": {
        "values": ["sum"]
      },
      "class_weights": {
        "values": ["balanced"]
      },
      "dataset": {
        "values": ["DCP"]
      },
      "homogeneous_conv": {
        "values": ["sage"]
      },
      "heterogeneous_conv": {
        "values": ["sage"]
      },
      "activation": {
        "values": ["leaky"]
      },
      "faz_node": {
        "values": [true]
      },
      "split": {
        "values": [1,2,3,4,5]
      },
      "start_rep": {
        "values": [false]
      },
      "aggr_faz": {
        "values": [false]
      },
      "smooth_label_loss": {
        "values": [true]
      },
      "skip_connection": {
        "values": [true]
      },
      "global_node": {
        "values": [false]
      },
      "SAM": {
        "values": [true]
      },
      "aggr_scheme": {
        "values": ["mean", "max", "sum", "lstm","std", ["mean", "max"], ["mean", "std"]]
      }
    }
  }
  